wishMe/__init__.py
wishMe-0.0.1.dist-info/METADATA
wishMe-0.0.1.dist-info/WHEEL
wishMe-0.0.1.dist-info/license .txt
wishMe-0.0.1.dist-info/top_level.txt
wishMe-0.0.1.dist-info/RECORD
